dspy_temporal/config.py
dspy_temporal/__init__.py
dspy_temporal/sandbox.py
dspy_temporal/context.py
dspy_temporal/plugin.py
dspy_temporal/py.typed
dspy_temporal/lm.py
dspy_temporal/module.py
dspy_temporal/workflow.py
dspy_temporal/tool.py
dspy_temporal/serialization.py
dspy_temporal-0.0.6.dist-info/WHEEL
dspy_temporal-0.0.6.dist-info/METADATA
dspy_temporal-0.0.6.dist-info/RECORD
