Metadata-Version: 2.4
Name: dspy-temporal
Version: 0.0.6
Summary: Durable execution for DSPy programs using Temporal workflows
Keywords: dspy,temporal,durable-execution,workflows,llm,ai,fault-tolerance,orchestration
Author: Barış Deniz Sağlam
Author-email: Barış Deniz Sağlam <bdsaglam@gmail.com>
License-Expression: MIT
Classifier: Development Status :: 3 - Alpha
Classifier: Intended Audience :: Developers
Classifier: License :: OSI Approved :: MIT License
Classifier: Operating System :: OS Independent
Classifier: Programming Language :: Python :: 3
Classifier: Programming Language :: Python :: 3.11
Classifier: Programming Language :: Python :: 3.12
Classifier: Programming Language :: Python :: 3.13
Classifier: Topic :: Scientific/Engineering :: Artificial Intelligence
Classifier: Topic :: Software Development :: Libraries :: Python Modules
Classifier: Typing :: Typed
Requires-Dist: dspy>=2.6.0
Requires-Dist: temporalio>=1.9.0
Requires-Python: >=3.11
Project-URL: Documentation, https://github.com/bdsaglam/dspy-temporal#readme
Project-URL: Homepage, https://github.com/bdsaglam/dspy-temporal
Project-URL: Issues, https://github.com/bdsaglam/dspy-temporal/issues
Project-URL: Repository, https://github.com/bdsaglam/dspy-temporal
